CHANGELOG.md
LICENSE
README.md
pypika_tortoise/__init__.py
pypika_tortoise/analytics.py
pypika_tortoise/dialects/__init__.py
pypika_tortoise/dialects/mssql.py
pypika_tortoise/dialects/mysql.py
pypika_tortoise/dialects/oracle.py
pypika_tortoise/dialects/postgresql.py
pypika_tortoise/dialects/sqlite.py
pypika_tortoise/enums.py
pypika_tortoise/exceptions.py
pypika_tortoise/functions.py
pypika_tortoise/pseudocolumns.py
pypika_tortoise/py.typed
pypika_tortoise/queries.py
pypika_tortoise/terms.py
pypika_tortoise/utils.py
pypika_tortoise-0.4.0.dist-info/LICENSE
pypika_tortoise-0.4.0.dist-info/METADATA
pypika_tortoise-0.4.0.dist-info/WHEEL
pypika_tortoise-0.4.0.dist-info/RECORD
